BCD.v
module bcdview (numin,numout);
input [3:0] numin;
output [7:0] numout;
reg [7:0] numout;
always@ (numin)
    case(numin)
        4'b0000:numout=8'hc0;
        4'b0001:numout=8'hf9;
        4'b0010:numout=8'ha4;
        4'b0011:numout=8'hb0;
        4'b0100:numout=8'h99;
        4'b0101:numout=8'h92;
        4'b0110:numout=8'h82;
        4'b0111:numout=8'hf8;
        4'b1000:numout=8'h80;
        4'b1001:numout=8'h90;
        default:numout=8'hff;
    endcase
endmodule

module dff (clk, D, Din, Load, Q4);
input clk, D, Din, Load;
output Q4;
reg Q4;
always@ (posedge clk)
    if (Load) Q4 = Din;
    else Q4 = D;
endmodule

module BCD(clk, rst_syn, load, load_num, Q_out, num_out);
input clk,rst_syn,load;
input [3:0] load_num;
output [3:0] Q_out;
wire [3:0] Q_out;
output [7:0] num_out;
wire [7:0] num_out;
reg Q0,Q1,Q2,Q3;
bcdview y1(Q_out,num_out);

dff x1(clk,Q0,Q0,load,Q_out[0]);
dff x2(clk,Q1,Q1,load,Q_out[1]);
dff x3(clk,Q2,Q2,load,Q_out[2]);
dff x4(clk,Q3,Q3,load,Q_out[3]);
always@ (posedge clk)
begin
    if (!rst_syn) begin
        Q0<=0;
        Q1<=0;
        Q2<=0;
        Q3<=0;
    end
    else if (load)begin
        Q0<=load_num[0];
        Q1<=load_num[1];
        Q2<=load_num[2];
        Q3<=load_num[3];
    end
    else begin
        if(Q0==1&&Q3==1)begin
            Q3<=0;
            Q0<=0;
        end
        else begin
            Q3<=Q3|(Q0&Q1&Q2);
            Q2<=(Q2&~Q1)|(Q0&Q1&~Q2)|(~Q0&Q2);
            Q1<=(Q0&~Q1)|(~Q0&Q1);
            Q0<=~Q0;
        end
    end
end
endmodule

testbench.v
`timescale 1ns/10ps
module bcd_tb;
reg clk,rst_syn,load;
reg [3:0] load_num;
wire [3:0] Q_out;
wire [7:0] num_out;
BCD ans (clk, rst_syn, load, load_num, Q_out, num_out);
initial begin
    clk=1;
    rst_syn=1;
    load=1;
    load_num=4'b0010;
end
always #50 clk=~clk;
initial #100 load=0;
initial #1300 load=1;
initial #1400 load=0;
initial #800 rst_syn=0;
initial #900 rst_syn=1;
initial #2000 $finish;
initial begin
$dumpfile("bcdans.vcd");
$dumpvars(0,ans);
end
endmodule

bcdans.vcd
$date
	Thu May 05 15:00:15 2022
$end
$version
	Icarus Verilog
$end
$timescale
	10ps
$end
$scope module bcd_tb $end
$scope module ans $end
$var wire 1 ! clk $end
$var wire 1 " load $end
$var wire 4 # load_num [3:0] $end
$var wire 1 $ rst_syn $end
$var wire 8 % num_out [7:0] $end
$var wire 4 & Q_out [3:0] $end
$var reg 1 ' Q0 $end
$var reg 1 ( Q1 $end
$var reg 1 ) Q2 $end
$var reg 1 * Q3 $end
$scope module x1 $end
$var wire 1 ' D $end
$var wire 1 ' Din $end
$var wire 1 " Load $end
$var wire 1 ! clk $end
$var reg 1 + Q4 $end
$upscope $end
$scope module x2 $end
$var wire 1 ( D $end
$var wire 1 ( Din $end
$var wire 1 " Load $end
$var wire 1 ! clk $end
$var reg 1 , Q4 $end
$upscope $end
$scope module x3 $end
$var wire 1 ) D $end
$var wire 1 ) Din $end
$var wire 1 " Load $end
$var wire 1 ! clk $end
$var reg 1 - Q4 $end
$upscope $end
$scope module x4 $end
$var wire 1 * D $end
$var wire 1 * Din $end
$var wire 1 " Load $end
$var wire 1 ! clk $end
$var reg 1 . Q4 $end
$upscope $end
$scope module y1 $end
$var wire 4 / numin [3:0] $end
$var reg 8 0 numout [7:0] $end
$upscope $end
$upscope $end
$upscope $end
$enddefinitions $end
#0
$dumpvars
bx 0
bx /
x.
x-
x,
x+
0*
0)
1(
0'
bx &
bx %
1$
b10 #
1"
1!
$end
#5000
0!
#10000
1'
b10100100 %
b10100100 0
0.
0-
1,
b10 &
b10 /
0+
1!
0"
#15000
0!
#20000
0'
0(
1)
b10110000 %
b10110000 0
b11 &
b11 /
1+
1!
#25000
0!
#30000
1'
b10011001 %
b10011001 0
1-
0,
b100 &
b100 /
0+
1!
#35000
0!
#40000
0'
1(
b10010010 %
b10010010 0
b101 &
b101 /
1+
1!
#45000
0!
#50000
1'
b10000010 %
b10000010 0
1,
b110 &
b110 /
0+
1!
#55000
0!
#60000
0'
0(
0)
1*
b11111000 %
b11111000 0
b111 &
b111 /
1+
1!
#65000
0!
#70000
1'
b10000000 %
b10000000 0
1.
0-
0,
b1000 &
b1000 /
0+
1!
#75000
0!
#80000
0*
0'
b10010000 %
b10010000 0
b1001 &
b1001 /
1+
1!
0$
#85000
0!
#90000
1'
b11000000 %
b11000000 0
0.
b0 &
b0 /
0+
1!
1$
#95000
0!
#100000
0'
1(
b11111001 %
b11111001 0
b1 &
b1 /
1+
1!
#105000
0!
#110000
1'
b10100100 %
b10100100 0
1,
b10 &
b10 /
0+
1!
#115000
0!
#120000
0'
0(
1)
b10110000 %
b10110000 0
b11 &
b11 /
1+
1!
#125000
0!
#130000
0)
1(
b10011001 %
b10011001 0
1-
0,
b100 &
b100 /
0+
1!
1"
#135000
0!
#140000
1'
b10100100 %
b10100100 0
1,
b10 &
b10 /
0-
1!
0"
#145000
0!
#150000
0'
0(
1)
b10110000 %
b10110000 0
b11 &
b11 /
1+
1!
#155000
0!
#160000
1'
b10011001 %
b10011001 0
0+
0,
b100 &
b100 /
1-
1!
#165000
0!
#170000
0'
1(
b10010010 %
b10010010 0
b101 &
b101 /
1+
1!
#175000
0!
#180000
1'
b10000010 %
b10000010 0
0+
b110 &
b110 /
1,
1!
#185000
0!
#190000
0'
0(
0)
1*
b11111000 %
b11111000 0
b111 &
b111 /
1+
1!
#195000
0!
#200000
1'
b10000000 %
b10000000 0
0+
0,
0-
b1000 &
b1000 /
1.
1!
